{"0": [{"cost_map": {"A": 2.62, "B": 1.46, "C": 2.21}, "utility_map": {"A": 5.27, "B": 6.77, "C": 5.75}, "capacity_map": {"A": 8, "B": 9, "C": 10}, "max_total_load": 18, "failure_prob_map": {"A": 0.0, "B": 0.0, "C": 0.001}, "exec_efficiency_coef": {"A": 2.0, "B": 2.0, "C": 2.0}}, {"cost_map": {"A": 1.57, "B": 1.53, "C": 2.07}, "utility_map": {"A": 7.75, "B": 8.32, "C": 9.77}, "capacity_map": {"A": 7, "B": 9, "C": 5}, "max_total_load": 18, "failure_prob_map": {"A": 0.001, "B": 0.001, "C": 0.001}, "exec_efficiency_coef": {"A": 2.0, "B": 2.0, "C": 2.0}}, {"cost_map": {"A": 3.31, "B": 4.16, "C": 4.28}, "utility_map": {"A": 6.32, "B": 5.33, "C": 6.43}, "capacity_map": {"A": 7, "B": 6, "C": 4}, "max_total_load": 18, "failure_prob_map": {"A": 0.0, "B": 0.0, "C": 0.001}, "exec_efficiency_coef": {"A": 2.0, "B": 2.0, "C": 2.0}}], "1": [{"cost_map": {"A": 2.93, "B": 2.34, "C": 1.13}, "utility_map": {"A": 4.13, "B": 5.74, "C": 5.2}, "capacity_map": {"A": 4, "B": 8, "C": 7}, "max_total_load": 18, "failure_prob_map": {"A": 0.001, "B": 0.0, "C": 0.001}, "exec_efficiency_coef": {"A": 2.0, "B": 2.0, "C": 2.0}}, {"cost_map": {"A": 3.86, "B": 4.12, "C": 3.43}, "utility_map": {"A": 7.32, "B": 8.58, "C": 7.48}, "capacity_map": {"A": 3, "B": 10, "C": 5}, "max_total_load": 18, "failure_prob_map": {"A": 0.0, "B": 0.001, "C": 0.0}, "exec_efficiency_coef": {"A": 2.0, "B": 2.0, "C": 2.0}}, {"cost_map": {"A": 2.37, "B": 2.14, "C": 1.95}, "utility_map": {"A": 5.65, "B": 4.71, "C": 6.44}, "capacity_map": {"A": 5, "B": 7, "C": 10}, "max_total_load": 18, "failure_prob_map": {"A": 0.001, "B": 0.001, "C": 0.0}, "exec_efficiency_coef": {"A": 2.0, "B": 2.0, "C": 2.0}}], "2": [{"cost_map": {"A": 4.82, "B": 3.9, "C": 3.07}, "utility_map": {"A": 4.93, "B": 5.0, "C": 4.15}, "capacity_map": {"A": 10, "B": 3, "C": 6}, "max_total_load": 18, "failure_prob_map": {"A": 0.001, "B": 0.001, "C": 0.001}, "exec_efficiency_coef": {"A": 2.0, "B": 2.0, "C": 2.0}}, {"cost_map": {"A": 1.06, "B": 2.65, "C": 1.62}, "utility_map": {"A": 4.63, "B": 6.72, "C": 4.64}, "capacity_map": {"A": 9, "B": 5, "C": 8}, "max_total_load": 18, "failure_prob_map": {"A": 0.001, "B": 0.001, "C": 0.0}, "exec_efficiency_coef": {"A": 2.0, "B": 2.0, "C": 2.0}}, {"cost_map": {"A": 3.25, "B": 3.11, "C": 3.19}, "utility_map": {"A": 9.23, "B": 7.29, "C": 9.31}, "capacity_map": {"A": 4, "B": 8, "C": 4}, "max_total_load": 18, "failure_prob_map": {"A": 0.001, "B": 0.001, "C": 0.001}, "exec_efficiency_coef": {"A": 2.0, "B": 2.0, "C": 2.0}}]}